psycopg2_utils/__init__.py
psycopg2_utils/cursor.py
psycopg2_utils/pool.py
psycopg2_utils/pooled_cursor_wrapper.py
psycopg2_utils-1.0.3.dist-info/LICENSE
psycopg2_utils-1.0.3.dist-info/METADATA
psycopg2_utils-1.0.3.dist-info/WHEEL
psycopg2_utils-1.0.3.dist-info/top_level.txt
psycopg2_utils-1.0.3.dist-info/RECORD
