Metadata-Version: 2.1
Name: psycopg2-utils
Version: 1.0.3
Summary: Utils to use with psycopg2 such as a connection pool and cursor
Home-page: https://github.com/lucinity/psycopg2-utils
Author: Lucinity
Author-email: gunnarsi@lucinity.com
License: MIT
Keywords: postgres psycopg2
Platform: any
Classifier: Development Status :: 5 - Production/Stable
Classifier: Intended Audience :: Developers
Classifier: Operating System :: OS Independent
Classifier: Programming Language :: Python :: 3
Requires-Python: >=3.8
License-File: LICENSE
Requires-Dist: psycopg2-binary
